networkx-stubs/__init__.pyi
networkx-stubs/convert.pyi
networkx-stubs/convert_matrix.pyi
networkx-stubs/exception.pyi
networkx-stubs/lazy_imports.pyi
networkx-stubs/relabel.pyi
networkx-stubs/algorithms/__init__.pyi
networkx-stubs/algorithms/asteroidal.pyi
networkx-stubs/algorithms/boundary.pyi
networkx-stubs/algorithms/bridges.pyi
networkx-stubs/algorithms/chains.pyi
networkx-stubs/algorithms/chordal.pyi
networkx-stubs/algorithms/clique.pyi
networkx-stubs/algorithms/cluster.pyi
networkx-stubs/algorithms/communicability_alg.pyi
networkx-stubs/algorithms/core.pyi
networkx-stubs/algorithms/covering.pyi
networkx-stubs/algorithms/cuts.pyi
networkx-stubs/algorithms/cycles.pyi
networkx-stubs/algorithms/d_separation.pyi
networkx-stubs/algorithms/dag.pyi
networkx-stubs/algorithms/distance_measures.pyi
networkx-stubs/algorithms/distance_regular.pyi
networkx-stubs/algorithms/dominance.pyi
networkx-stubs/algorithms/dominating.pyi
networkx-stubs/algorithms/efficiency_measures.pyi
networkx-stubs/algorithms/euler.pyi
networkx-stubs/algorithms/graph_hashing.pyi
networkx-stubs/algorithms/graphical.pyi
networkx-stubs/algorithms/hierarchy.pyi
networkx-stubs/algorithms/hybrid.pyi
networkx-stubs/algorithms/isolate.pyi
networkx-stubs/algorithms/link_prediction.pyi
networkx-stubs/algorithms/lowest_common_ancestors.pyi
networkx-stubs/algorithms/matching.pyi
networkx-stubs/algorithms/mis.pyi
networkx-stubs/algorithms/moral.pyi
networkx-stubs/algorithms/non_randomness.pyi
networkx-stubs/algorithms/planar_drawing.pyi
networkx-stubs/algorithms/planarity.pyi
networkx-stubs/algorithms/reciprocity.pyi
networkx-stubs/algorithms/regular.pyi
networkx-stubs/algorithms/richclub.pyi
networkx-stubs/algorithms/similarity.pyi
networkx-stubs/algorithms/simple_paths.pyi
networkx-stubs/algorithms/smallworld.pyi
networkx-stubs/algorithms/smetric.pyi
networkx-stubs/algorithms/sparsifiers.pyi
networkx-stubs/algorithms/structuralholes.pyi
networkx-stubs/algorithms/summarization.pyi
networkx_stubs-0.0.1.dist-info/METADATA
networkx_stubs-0.0.1.dist-info/WHEEL
networkx_stubs-0.0.1.dist-info/top_level.txt
networkx_stubs-0.0.1.dist-info/RECORD
