Metadata-Version: 2.1
Name: networkx-stubs
Version: 0.0.1
Summary: Typing stubs for NetworkX
Home-page: https://github.com/eggplants/networkx-stubs
Author: eggplants
Author-email: w10776e8w@yahoo.co.jp
Classifier: Intended Audience :: Developers
Classifier: Programming Language :: Python
Requires-Dist: networkx
Provides-Extra: dev
Requires-Dist: black ; extra == 'dev'
Requires-Dist: flake8-black ; extra == 'dev'
Requires-Dist: mypy ; extra == 'dev'
Requires-Dist: flake8 ; extra == 'dev'
Requires-Dist: flake8-pyi ; extra == 'dev'
Requires-Dist: setuptools ; extra == 'dev'
Requires-Dist: wheel ; extra == 'dev'
